django_genericfilters/__init__.py
django_genericfilters/fields.py
django_genericfilters/forms.py
django_genericfilters/models.py
django_genericfilters/views.py
django_genericfilters/static/css/filters_list.css
django_genericfilters/static/css/genericfilters.css
django_genericfilters/static/js/genericfilters.js
django_genericfilters/templates/genericfilters/filter_list.html
django_genericfilters/templates/genericfilters/order_by_list.html
django_genericfilters/templates/genericfilters/query_filter.html
django_genericfilters/templates/snippets/pagination.html
django_genericfilters/templatetags/__init__.py
django_genericfilters/templatetags/paginator.py
django_genericfilters/templatetags/updateurl.py
django_genericfilters/templatetags/utils.py
django_genericfilters/tests/__init__.py
django_genericfilters/tests/test_fields.py
django_genericfilters/tests/test_forms.py
django_genericfilters/tests/test_templatetags.py
django_genericfilters/tests/test_views.py
django_generic_filters-2.1.1.dist-info/AUTHORS
django_generic_filters-2.1.1.dist-info/LICENSE
django_generic_filters-2.1.1.dist-info/METADATA
django_generic_filters-2.1.1.dist-info/WHEEL
django_generic_filters-2.1.1.dist-info/top_level.txt
django_generic_filters-2.1.1.dist-info/zip-safe
django_generic_filters-2.1.1.dist-info/RECORD
