Metadata-Version: 2.1
Name: django-generic-filters
Version: 2.1.1
Summary: Easy filters for your Generic ListView with Django.
Home-page: https://github.com/peopledoc/django-generic-filters
Author: PeopleDoc
Author-email: peopleask@novapost.fr
License: BSD
Project-URL: GitHub, https://github.com/peopledoc/django-generic-filters
Project-URL: Changelog, https://github.com/peopledoc/django-generic-filters/releases
Project-URL: Issue tracker, https://github.com/peopledoc/django-generic-filters/issues
Project-URL: Documentation, https://django-generic-filters.readthedocs.io
Keywords: class-based view,generic view,filters
Platform: UNKNOWN
Classifier: Development Status :: 5 - Production/Stable
Classifier: License :: OSI Approved :: BSD License
Classifier: Programming Language :: Python :: 3
Classifier: Programming Language :: Python :: 3.7
Classifier: Programming Language :: Python :: 3.8
Classifier: Programming Language :: Python :: 3.9
Classifier: Programming Language :: Python :: 3.10
Classifier: Framework :: Django :: 2.2
Classifier: Framework :: Django :: 3.0
Classifier: Framework :: Django :: 3.1
Classifier: Framework :: Django :: 3.2
Classifier: Framework :: Django :: 4.0
Provides-Extra: dev
License-File: LICENSE
License-File: AUTHORS
